[
  {
    "id": "1",
    "title": "いびきは体のSOS？\n放置してはいけない5つの理由",
    "summary": "いびきには口呼吸型、鼻づまり型など複数のタイプがあります。放置するとどんなリスクがあるのか解説します。",
    "url": "https://yusukematsui-cloud.github.io/ibiki-navi-articles/article_01_ibiki_sos.html",
    "imageUrl": "https://yusukematsui-cloud.github.io/ibiki-navi-articles/hero.jpg",
    "date": "2026-02-16"
  },
  {
    "id": "2",
    "title": "いびきは体に悪い？\n放置してはいけない3つの医学的理由",
    "summary": "いびきの健康リスクとよくある誤解を医学的根拠とともに解説します。",
    "url": "https://yusukematsui-cloud.github.io/ibiki-navi-articles/day2_v4.html",
    "imageUrl": "https://yusukematsui-cloud.github.io/ibiki-navi-articles/heart-brain.jpg",
    "date": "2026-03-09"
  }
]
